vmon/__init__.py
vmon/main.py
vmon/spectrum.py
vmon/commands/__init__.py
vmon/commands/export.py
vmon/commands/plot.py
vmon_cli-0.2.0.dist-info/LICENSE
vmon_cli-0.2.0.dist-info/METADATA
vmon_cli-0.2.0.dist-info/WHEEL
vmon_cli-0.2.0.dist-info/entry_points.txt
vmon_cli-0.2.0.dist-info/top_level.txt
vmon_cli-0.2.0.dist-info/RECORD
