Metadata-Version: 2.1
Name: vmon-cli
Version: 0.2.0
Summary: CLI Viewer for Ibsen 512 USB interrogator
Home-page: https://github.com/codenio/vmon-cli
Author: Aananth K
Author-email: aananthraj1995@gmail.com
License: GPL-3.0
Platform: UNKNOWN
Requires-Dist: click (==7.1.2)
Requires-Dist: cycler (==0.10.0)
Requires-Dist: DateTime (==4.3)
Requires-Dist: kiwisolver (==1.3.1)
Requires-Dist: matplotlib (==3.3.3)
Requires-Dist: numpy (==1.19.4)
Requires-Dist: pandas (==1.1.5)
Requires-Dist: Pillow (==8.0.1)
Requires-Dist: pyparsing (==2.4.7)
Requires-Dist: python-dateutil (==2.8.1)
Requires-Dist: pytz (==2020.4)
Requires-Dist: scipy (==1.5.4)
Requires-Dist: six (==1.15.0)
Requires-Dist: zope.interface (==5.2.0)
